hasasia/__init__.py
hasasia/sensitivity.py
hasasia/sim.py
hasasia/skymap.py
hasasia/utils.py
hasasia/sensitivity_curves/nanograv_11yr_deter.sc
hasasia/sensitivity_curves/nanograv_11yr_stoch.sc
hasasia-1.2.3.dist-info/AUTHORS.rst
hasasia-1.2.3.dist-info/LICENSE
hasasia-1.2.3.dist-info/METADATA
hasasia-1.2.3.dist-info/WHEEL
hasasia-1.2.3.dist-info/top_level.txt
hasasia-1.2.3.dist-info/RECORD
