Metadata-Version: 2.1
Name: hasasia
Version: 1.2.3
Summary: A Python package to calculate gravitational-wave sensitivity curves for pulsar timing arrays.
Home-page: https://github.com/Hazboun6/hasasia
Author: Jeffrey S. Hazboun
Author-email: jeffrey.hazboun@gmail.com
License: MIT license
Keywords: hasasia
Platform: UNKNOWN
Classifier: Development Status :: 2 - Pre-Alpha
Classifier: Intended Audience :: Developers
Classifier: License :: OSI Approved :: MIT License
Classifier: Natural Language :: English
Classifier: Programming Language :: Python :: 3
Classifier: Programming Language :: Python :: 3.4
Classifier: Programming Language :: Python :: 3.5
Classifier: Programming Language :: Python :: 3.6
Classifier: Programming Language :: Python :: 3.7
License-File: LICENSE
License-File: AUTHORS.rst
Requires-Dist: numpy
Requires-Dist: scipy
Requires-Dist: astropy
